promise/__init__.py
promise/async_.py
promise/compat.py
promise/context.py
promise/dataloader.py
promise/iterate_promise.py
promise/promise.py
promise/promise_list.py
promise/utils.py
promise/pyutils/__init__.py
promise/pyutils/version.py
promise/schedulers/__init__.py
promise/schedulers/asyncio.py
promise/schedulers/gevent.py
promise/schedulers/immediate.py
promise/schedulers/thread.py
promise-2.2.1.dist-info/DESCRIPTION.rst
promise-2.2.1.dist-info/METADATA
promise-2.2.1.dist-info/RECORD
promise-2.2.1.dist-info/WHEEL
promise-2.2.1.dist-info/metadata.json
promise-2.2.1.dist-info/top_level.txt
