Metadata-Version: 1.1
Name: promise
Version: 2.2.1
Summary: Promises/A+ implementation for Python
Home-page: https://github.com/syrusakbary/promise
Author: Syrus Akbary
Author-email: me@syrusakbary.com
License: MIT
Download-URL: https://github.com/syrusakbary/promise/releases
Keywords: concurrent future deferred promise
Platform: UNKNOWN
Classifier: Development Status :: 5 - Production/Stable
Classifier: Intended Audience :: Developers
Classifier: Topic :: Software Development :: Libraries
Classifier: Programming Language :: Python :: 2
Classifier: Programming Language :: Python :: 2.7
Classifier: Programming Language :: Python :: 3
Classifier: Programming Language :: Python :: 3.3
Classifier: Programming Language :: Python :: 3.4
Classifier: Programming Language :: Python :: 3.5
Classifier: Programming Language :: Python :: Implementation :: PyPy
Classifier: License :: OSI Approved :: MIT License
